edgescan/__init__.py
edgescan/api/__init__.py
edgescan/api/authentication.py
edgescan/api/client.py
edgescan/api/session.py
edgescan/caching.py
edgescan/cli/__init__.py
edgescan/cli/__main__.py
edgescan/cli/command_groups/__init__.py
edgescan/cli/command_groups/assets.py
edgescan/cli/command_groups/data_exports.py
edgescan/cli/command_groups/hosts.py
edgescan/cli/command_groups/licenses.py
edgescan/cli/command_groups/vulnerabilities.py
edgescan/cli/helpers.py
edgescan/constants.py
edgescan/data/__init__.py
edgescan/data/parser.py
edgescan/data/types/__init__.py
edgescan/data/types/assessment.py
edgescan/data/types/asset.py
edgescan/data/types/base.py
edgescan/data/types/host.py
edgescan/data/types/license.py
edgescan/data/types/location_specifier.py
edgescan/data/types/vulnerability.py
edgescan/errors.py
edgescan/logging.py
edgescan/patterns.py
edgescan/platforms.py
edgescan/serialization.py
edgescan/tallies.py
edgescan/time.py
edgescan/type_hints.py
edgescan/types.py
edgescan-2.3.1.dist-info/entry_points.txt
edgescan-2.3.1.dist-info/LICENSE.md
edgescan-2.3.1.dist-info/WHEEL
edgescan-2.3.1.dist-info/METADATA
edgescan-2.3.1.dist-info/RECORD
