Metadata-Version: 2.1
Name: edgescan
Version: 2.3.1
Summary: An API client for EdgeScan
License: MIT
Author: Tyler Fisher
Author-email: tyler.fisher@canadalife.com
Requires-Python: >=3.8,<4.0
Classifier: License :: OSI Approved :: MIT License
Classifier: Programming Language :: Python :: 3
Classifier: Programming Language :: Python :: 3.10
Classifier: Programming Language :: Python :: 3.8
Classifier: Programming Language :: Python :: 3.9
Requires-Dist: click (>=8.1.3,<9.0.0)
Requires-Dist: inflection (>=0.5.1,<0.6.0)
Requires-Dist: python-dateutil (>=2.8.2,<3.0.0)
Requires-Dist: requests (>=2.28.0,<3.0.0)
Requires-Dist: urllib3 (>=1.26.9,<2.0.0)
